ado_backlog_cli/__init__.py
ado_backlog_cli/cli.py
ado_backlog_cli/commands/__init__.py
ado_backlog_cli/config.py
ado_backlog_cli/log_config.py
ado_backlog_cli/report_generator/__init__.py
ado_backlog_cli/report_generator/csv_report.py
ado_backlog_cli/report_generator/report_generator.py
ado_backlog_cli/report_generator/table_report.py
ado_backlog_cli/report_generator/word_report.py
ado_backlog_cli/utils/__init__.py
ado_backlog_cli/utils/helper.py
ado_backlog_cli/work_item_ado_wrapper.py
ado_backlog_cli/work_item_manager.py
ado_backlog_cli/work_item_utils.py
ado_backlog_cli-0.1.8.dist-info/METADATA
ado_backlog_cli-0.1.8.dist-info/WHEEL
ado_backlog_cli-0.1.8.dist-info/entry_points.txt
ado_backlog_cli-0.1.8.dist-info/RECORD
